hdl_if/__build_num__.py
hdl_if/__init__.py
hdl_if/__main__.py
hdl_if/backend.py
hdl_if/decorators.py
hdl_if/hdl_obj_rgy.py
hdl_if/hdl_services.py
hdl_if/libpyhdl_if.so
hdl_if/pkginfo.py
hdl_if/pytest_runner.py
hdl_if/call/call_proxy.py
hdl_if/call/hdl_call_endpoint.py
hdl_if/cmd/cmd_api_gen_sv.py
hdl_if/cmd/cmd_ifc_gen_sv.py
hdl_if/cmd/cmd_ifc_gen_types.py
hdl_if/cmd/cmd_libs.py
hdl_if/cmd/cmd_share.py
hdl_if/dfm/__ext__.py
hdl_if/dfm/__init__.py
hdl_if/dfm/api_gen_sv.py
hdl_if/dfm/dpi_lib.py
hdl_if/dfm/flow.dv
hdl_if/dfm/sv_pkg.py
hdl_if/dfm/uvm_pkg.py
hdl_if/dfm/vpi_lib.py
hdl_if/impl/__init__.py
hdl_if/impl/decl_rgy.py
hdl_if/impl/output_flush.py
hdl_if/impl/typeinfo.py
hdl_if/impl/call/__init__.py
hdl_if/impl/call/api_def.py
hdl_if/impl/call/api_def_from_json.py
hdl_if/impl/call/api_def_rgy.py
hdl_if/impl/call/call_proxy_dpi.py
hdl_if/impl/call/context.py
hdl_if/impl/call/ctor.py
hdl_if/impl/call/gen_py_class.py
hdl_if/impl/call/gen_sv_class.py
hdl_if/impl/call/hdl_call_endpoint_dpi.py
hdl_if/impl/call/imp_func_impl.py
hdl_if/impl/call/imp_task_impl.py
hdl_if/impl/call/method_def.py
hdl_if/impl/dpi/__init__.py
hdl_if/impl/dpi/hdl_services_dpi.py
hdl_if/impl/pi/__init__.py
hdl_if/impl/pi/backend_asyncio.py
hdl_if/impl/pi/backend_cocotb.py
hdl_if/impl/tlm/__init__.py
hdl_if/impl/tlm/gen_ifc_sv.py
hdl_if/impl/tlm/gen_ifc_types.py
hdl_if/impl/tlm/model_info_tlm_if.py
hdl_if/impl/tlm/stream.py
hdl_if/impl/tlm/stream_req.py
hdl_if/impl/tlm/stream_req_rsp.py
hdl_if/impl/tlm/stream_rsp.py
hdl_if/impl/tlm/type_info_tlm_if.py
hdl_if/impl/vpi/__init__.py
hdl_if/impl/vpi/api.py
hdl_if/impl/vpi/call_api.py
hdl_if/impl/vpi/call_proxy_vpi.py
hdl_if/impl/vpi/pkg_tf.py
hdl_if/impl/vpi/pytf.py
hdl_if/impl/vpi/tlm_api.py
hdl_if/impl/vpi/util.py
hdl_if/pi/__init__.py
hdl_if/share/pyhdl_if.core
hdl_if/share/pyhdl_if_req_fifo.sv
hdl_if/share/pyhdl_if_reqrsp_fifo.sv
hdl_if/share/pyhdl_if_rsp_fifo.sv
pyhdl_if-0.2.0.21303180869.dist-info/METADATA
pyhdl_if-0.2.0.21303180869.dist-info/WHEEL
pyhdl_if-0.2.0.21303180869.dist-info/entry_points.txt
pyhdl_if-0.2.0.21303180869.dist-info/top_level.txt
pyhdl_if-0.2.0.21303180869.dist-info/RECORD
pyhdl_if-0.2.0.21303180869.dist-info/licenses/LICENSE
