Metadata-Version: 2.1
Name: pyhdl-if
Version: 0.2.0.21303180869
Summary: Python interface for HDL programming interfaces
Home-page: https://github.com/fvutils/pyhdl-if
Author: Matthew Ballance
Author-email: matt.ballance@gmail.com
License: Apache 2.0
Keywords: SystemVerilog,Verilog,VHDL,RTL,Python
License-File: LICENSE
Provides-Extra: pytest
Requires-Dist: pytest; extra == "pytest"
Requires-Dist: pytest-asyncio; extra == "pytest"
